prisoners_dilemma/__init__.py
prisoners_dilemma/bots/__init__.py
prisoners_dilemma/bots/bots.py
prisoners_dilemma/population/__init__.py
prisoners_dilemma/population/population.py
prisoners_dilemma/tournament/__init__.py
prisoners_dilemma/tournament/tournament.py
prisoners_dilemma-1.0.dist-info/METADATA
prisoners_dilemma-1.0.dist-info/WHEEL
prisoners_dilemma-1.0.dist-info/entry_points.txt
prisoners_dilemma-1.0.dist-info/top_level.txt
prisoners_dilemma-1.0.dist-info/RECORD
